Snowforge/AWSIntegration.py
Snowforge/Config.py
Snowforge/Logging.py
Snowforge/SnowflakeIntegration.py
Snowforge/SnowflakeLogging.py
Snowforge/__init__.py
Snowforge/DataMover/DataMover.py
Snowforge/DataMover/__init__.py
Snowforge/DataMover/Extractors/ExtractorStrategy.py
Snowforge/DataMover/Extractors/NetezzaExtractor.py
Snowforge/DataMover/Extractors/__init__.py
snowforge_package-0.3.34.dist-info/licenses/LICENSE
snowforge_package-0.3.34.dist-info/METADATA
snowforge_package-0.3.34.dist-info/WHEEL
snowforge_package-0.3.34.dist-info/top_level.txt
snowforge_package-0.3.34.dist-info/RECORD
