Metadata-Version: 2.4
Name: snowforge-package
Version: 0.3.34
Summary: A Python package for supporting migration from on-prem to cloud
Home-page: https://github.com/yourusername/Snowforge
Author: Andreas Heggelund
Author-email: andreasheggelund@gmail.com
Classifier: Programming Language :: Python :: 3
Classifier: License :: OSI Approved :: MIT License
Classifier: Operating System :: OS Independent
Requires-Python: >=3.12
License-File: LICENSE
Requires-Dist: boto3
Requires-Dist: snowflake-connector-python
Requires-Dist: coloredlogs
Requires-Dist: colored
Requires-Dist: tqdm
Requires-Dist: toml
Requires-Dist: argparse
Dynamic: author
Dynamic: author-email
Dynamic: classifier
Dynamic: description
Dynamic: description-content-type
Dynamic: home-page
Dynamic: license-file
Dynamic: requires-dist
Dynamic: requires-python
Dynamic: summary
